pytest_capsqlalchemy/__init__.py
pytest_capsqlalchemy/capturer.py
pytest_capsqlalchemy/context.py
pytest_capsqlalchemy/expression.py
pytest_capsqlalchemy/plugin.py
pytest_capsqlalchemy/utils.py
pytest_capsqlalchemy-0.2.1.dist-info/METADATA
pytest_capsqlalchemy-0.2.1.dist-info/WHEEL
pytest_capsqlalchemy-0.2.1.dist-info/entry_points.txt
pytest_capsqlalchemy-0.2.1.dist-info/licenses/LICENSE
pytest_capsqlalchemy-0.2.1.dist-info/RECORD
