Metadata-Version: 2.4
Name: pytest-capsqlalchemy
Version: 0.2.1
Summary: Pytest plugin to allow capturing SQLAlchemy queries.
Project-URL: Homepage, https://softwareone-platform.github.io/pytest-capsqlalchemy/
Project-URL: Repository, https://github.com/softwareone-platform/pytest-capsqlalchemy
Project-URL: Documentation, https://softwareone-platform.github.io/pytest-capsqlalchemy/
Author: SoftwareOne AG
License-Expression: Apache-2.0
License-File: LICENSE
Keywords: python
Classifier: Development Status :: 4 - Beta
Classifier: Framework :: AsyncIO
Classifier: Framework :: Pytest
Classifier: Intended Audience :: Developers
Classifier: Operating System :: OS Independent
Classifier: Programming Language :: Python
Classifier: Programming Language :: Python :: 3 :: Only
Classifier: Programming Language :: Python :: 3.9
Classifier: Programming Language :: Python :: 3.10
Classifier: Programming Language :: Python :: 3.11
Classifier: Programming Language :: Python :: 3.12
Classifier: Programming Language :: Python :: 3.13
Classifier: Topic :: Database :: Front-Ends
Classifier: Topic :: Software Development :: Libraries :: Python Modules
Classifier: Topic :: Software Development :: Testing
Classifier: Typing :: Typed
Requires-Python: <4.0,>=3.9
Requires-Dist: sqlalchemy[asyncio]>=2.0.38
